{
  "schema_version": 2,
  "generated_at": "2026-07-19T14:12:35.236724+00:00",
  "source_plan": "Live MM calendar board 18388590642",
  "board_id": "2109172490",
  "view_id": "57490550",
  "subitem_board_id": "2109172677",
  "day": "2026-07-26",
  "parent_day": "2026-07-26",
  "promo_time": "11:00 UTC",
  "requires_review": false,
  "task_count": 8,
  "tasks": [
    {
      "parent_day": "2026-07-26",
      "source_calendar_day": "2026-07-26",
      "source_row_name": "Crazy Train Activities",
      "source_mm_item_id": "12217448067",
      "source_detail": "Required mechanic/config details are missing from the MM source.",
      "config_status": null,
      "creative_label": null,
      "task_name": "Crazy Train Activities",
      "product": "Event",
      "pricing": null,
      "template_source": null,
      "start_date": "2026-07-26",
      "end_date": "2026-07-28",
      "start_at": "2026-07-26 11:00 UTC",
      "end_at": "2026-07-28 11:00 UTC",
      "start_time": "11:00:00",
      "end_time": "11:00:00",
      "monday_start_date": "2026-07-26",
      "monday_start_time": "08:00:00",
      "monday_end_date": "2026-07-28",
      "monday_end_time": "08:00:00",
      "monday_display_offset_hours": 3,
      "due_date": "2026-07-24",
      "m_and_m_status": "More Info required",
      "times_per_player": "Multiple",
      "reuse": false,
      "recent_ops_reference": "No recent Ops precedent found (2026-04-01 through 2026-07-25)",
      "requires_review": false,
      "warnings": [],
      "description": "Segment: All Users\nPrize: Not specified in MM source"
    },
    {
      "parent_day": "2026-07-26",
      "source_calendar_day": "2026-07-26",
      "source_row_name": "MES - Crazy train machines",
      "source_mm_item_id": "12228749758",
      "source_detail": "48 hours MES \nplayers will have different missions only n the crazy train machines. \n\nmilestone 1 \nspin x times in crazy train express machine \nprize - 3 SNL Dice & 2 * reg\n\nmilestone 2 \nwin x jackpots in even more crazy train machine \nprize - snl multiwheel and 2 hammers \n\nmilestone 3 \nwin x times in crazy train deluxe machine \nprize - 3* ace card and 4 hammers",
      "config_status": "Config needed",
      "creative_label": null,
      "task_name": "MES - Crazy train machines",
      "product": "Core",
      "pricing": null,
      "template_source": null,
      "start_date": "2026-07-26",
      "end_date": "2026-07-28",
      "start_at": "2026-07-26 11:00 UTC",
      "end_at": "2026-07-28 11:00 UTC",
      "start_time": "11:00:00",
      "end_time": "11:00:00",
      "monday_start_date": "2026-07-26",
      "monday_start_time": "08:00:00",
      "monday_end_date": "2026-07-28",
      "monday_end_time": "08:00:00",
      "monday_display_offset_hours": 3,
      "due_date": "2026-07-24",
      "m_and_m_status": "Missing Art+Config",
      "times_per_player": "Multiple",
      "reuse": false,
      "recent_ops_reference": "2026-05-22 item 12032801952 (MES - Purchase Streak)",
      "requires_review": false,
      "warnings": [],
      "description": "Segment: All Users\nbanner - open M.E.S\n\nMission: players will have different missions only n the crazy train machines\n\nMilestone 1:\nMission: spin x times in crazy train express machine\nPrize: 3 SNL Dice & 2 * reg\n\nMilestone 2:\nMission: win x jackpots in even more crazy train machine\nPrize: snl multiwheel and 2 hammers\n\nMilestone 3:\nMission: win x times in crazy train deluxe machine\nPrize: 3* ace card and 4 hammers"
    },
    {
      "parent_day": "2026-07-26",
      "source_calendar_day": "2026-07-26",
      "source_row_name": "MGAP - BOGO",
      "source_mm_item_id": "12228782399",
      "source_detail": "Required mechanic/config details are missing from the MM source.",
      "config_status": null,
      "creative_label": null,
      "task_name": "MGAP - BOGO",
      "product": "MGAP",
      "pricing": null,
      "template_source": {
        "group_id": "group_mkv1vqxx",
        "group_title": "MGAP"
      },
      "start_date": "2026-07-26",
      "end_date": "2026-07-27",
      "start_at": "2026-07-26 11:00 UTC",
      "end_at": "2026-07-27 11:00 UTC",
      "start_time": "11:00:00",
      "end_time": "11:00:00",
      "monday_start_date": "2026-07-26",
      "monday_start_time": "08:00:00",
      "monday_end_date": "2026-07-27",
      "monday_end_time": "08:00:00",
      "monday_display_offset_hours": 3,
      "due_date": "2026-07-24",
      "m_and_m_status": "Waiting for MM Approval",
      "times_per_player": "Once",
      "reuse": true,
      "recent_ops_reference": "2026-05-30 item 11869424484 (MGAP BOGO Extreme OR Epic)",
      "requires_review": false,
      "warnings": [],
      "description": "Segment: All Users\nVariant: BOGO\nMake sure to set UI for both Extreme + Epic"
    },
    {
      "parent_day": "2026-07-26",
      "source_calendar_day": "2026-07-26",
      "source_row_name": "DD - 8 hammers",
      "source_mm_item_id": "12228821949",
      "source_detail": "Required mechanic/config details are missing from the MM source.",
      "config_status": null,
      "creative_label": null,
      "task_name": "DD - 8 hammers | H Pricing",
      "product": "Daily deal",
      "pricing": "High",
      "template_source": {
        "group_id": "group_mkv1971m",
        "group_title": "Daily Deal"
      },
      "start_date": "2026-07-26",
      "end_date": "2026-07-27",
      "start_at": "2026-07-26 11:00 UTC",
      "end_at": "2026-07-27 11:00 UTC",
      "start_time": "11:00:00",
      "end_time": "11:00:00",
      "monday_start_date": "2026-07-26",
      "monday_start_time": "08:00:00",
      "monday_end_date": "2026-07-27",
      "monday_end_time": "08:00:00",
      "monday_display_offset_hours": 3,
      "due_date": "2026-07-24",
      "m_and_m_status": "Waiting for MM Approval",
      "times_per_player": "Multiple",
      "reuse": true,
      "recent_ops_reference": "2026-05-22 item 12032719754 (DD - 8 hammers | H Price)",
      "requires_review": false,
      "warnings": [],
      "description": "Segment: All Users\nPrizes: 8 hammers\nPricing: High"
    },
    {
      "parent_day": "2026-07-26",
      "source_calendar_day": "2026-07-26",
      "source_row_name": "Prize Mania",
      "source_mm_item_id": "12228826366",
      "source_detail": "coins\ngems\n4 rds\n1 ggs\n150% SB \n3 SNL dice",
      "config_status": "Config needed",
      "creative_label": null,
      "task_name": "Prize Mania | H Pricing",
      "product": "Prize Mania",
      "pricing": "High",
      "template_source": null,
      "start_date": "2026-07-26",
      "end_date": "2026-07-27",
      "start_at": "2026-07-26 11:00 UTC",
      "end_at": "2026-07-27 11:00 UTC",
      "start_time": "11:00:00",
      "end_time": "11:00:00",
      "monday_start_date": "2026-07-26",
      "monday_start_time": "08:00:00",
      "monday_end_date": "2026-07-27",
      "monday_end_time": "08:00:00",
      "monday_display_offset_hours": 3,
      "due_date": "2026-07-24",
      "m_and_m_status": "Missing Config",
      "times_per_player": "Once",
      "reuse": true,
      "recent_ops_reference": "2026-04-13 item 11727784931 (Prize Mania (FB))",
      "requires_review": false,
      "warnings": [],
      "description": "Reset at 00:00 UTC\n\nSegment: All Users\nPrizes: coins, gems, 4 rds, 1 ggs, 150% SB, 3 SNL dice\nPricing: High"
    },
    {
      "parent_day": "2026-07-26",
      "source_calendar_day": "2026-07-26",
      "source_row_name": "PO - coin grab-  crazy train machine",
      "source_mm_item_id": "12228833942",
      "source_detail": "PO for players to purchase coins and coins grab crazy train machine on top of the coins\n\nonce per player",
      "config_status": null,
      "creative_label": null,
      "task_name": "PO - coin grab- crazy train machine",
      "product": "Offers & coin sale",
      "pricing": null,
      "template_source": null,
      "start_date": "2026-07-26",
      "end_date": "2026-07-27",
      "start_at": "2026-07-26 11:00 UTC",
      "end_at": "2026-07-27 11:00 UTC",
      "start_time": "11:00:00",
      "end_time": "11:00:00",
      "monday_start_date": "2026-07-26",
      "monday_start_time": "08:00:00",
      "monday_end_date": "2026-07-27",
      "monday_end_time": "08:00:00",
      "monday_display_offset_hours": 3,
      "due_date": "2026-07-24",
      "m_and_m_status": "Waiting for MM Approval",
      "times_per_player": "Once",
      "reuse": false,
      "recent_ops_reference": "2026-04-25 item 11827811018 (PO - finish the chase now 21:00-23:00 UTC - H Price)",
      "requires_review": false,
      "warnings": [],
      "description": "Currency: Coins\nSegment: PU\nAmount: coin grab- crazy train machine\nSegment: PRAS\nAmount: Not specified in MM source"
    },
    {
      "parent_day": "2026-07-26",
      "source_calendar_day": "2026-07-26",
      "source_row_name": "Shiny Show - Different Prizes",
      "source_mm_item_id": "12228853941",
      "source_detail": "coins \ngems\nhammers \nreg cards \nsnl dice",
      "config_status": "Done",
      "creative_label": null,
      "task_name": "Shiny Show - Different Prizes",
      "product": "Album",
      "pricing": null,
      "template_source": null,
      "start_date": "2026-07-26",
      "end_date": "2026-07-27",
      "start_at": "2026-07-26 11:00 UTC",
      "end_at": "2026-07-27 11:00 UTC",
      "start_time": "11:00:00",
      "end_time": "11:00:00",
      "monday_start_date": "2026-07-26",
      "monday_start_time": "08:00:00",
      "monday_end_date": "2026-07-27",
      "monday_end_time": "08:00:00",
      "monday_display_offset_hours": 3,
      "due_date": "2026-07-24",
      "m_and_m_status": "Waiting for MM Approval",
      "times_per_player": "Multiple",
      "reuse": true,
      "recent_ops_reference": "2026-05-21 item 12032646636 (Shiny Show - Different Prizes)",
      "requires_review": false,
      "warnings": [],
      "description": "Segment: All Users\nVariant: Different Prizes"
    },
    {
      "parent_day": "2026-07-26",
      "source_calendar_day": "2026-07-26",
      "source_row_name": "DPU 14+ | Seasonal Offer 100% Sale",
      "source_mm_item_id": "12370458975",
      "source_detail": "Required mechanic/config details are missing from the MM source.",
      "config_status": null,
      "creative_label": null,
      "task_name": "DPU 14+ | Seasonal Offer 100% Sale",
      "product": "Short Term",
      "pricing": null,
      "template_source": null,
      "start_date": "2026-07-26",
      "end_date": "2026-07-27",
      "start_at": "2026-07-26 11:00 UTC",
      "end_at": "2026-07-27 11:00 UTC",
      "start_time": "11:00:00",
      "end_time": "11:00:00",
      "monday_start_date": "2026-07-26",
      "monday_start_time": "08:00:00",
      "monday_end_date": "2026-07-27",
      "monday_end_time": "08:00:00",
      "monday_display_offset_hours": 3,
      "due_date": "2026-07-24",
      "m_and_m_status": "Waiting for MM Approval",
      "times_per_player": null,
      "reuse": true,
      "recent_ops_reference": "2026-05-06 item 11889455894 (DPU NPU PO 400% Sale)",
      "requires_review": false,
      "warnings": [],
      "description": "Segment: DPU\nPrize: DPU 14+ | Seasonal Offer 100% Sale"
    }
  ]
}
